LICENSE
MANIFEST.in
setup.py
pylint_common/__init__.py
pylint_common/augmentations.py
pylint_common.egg-info/PKG-INFO
pylint_common.egg-info/SOURCES.txt
pylint_common.egg-info/dependency_links.txt
pylint_common.egg-info/not-zip-safe
pylint_common.egg-info/requires.txt
pylint_common.egg-info/top_level.txt
test/test_func.py