Metadata-Version: 1.1
Name: pylint-common
Version: 0.2.4
Summary: pylint-common is a Pylint plugin to improve Pylint error analysis of the standard Python library
Home-page: https://github.com/landscapeio/pylint-common
Author: landscape.io
Author-email: code@landscape.io
License: GPLv2
Keywords: pylint stdlib plugin
Platform: UNKNOWN
Classifier: Development Status :: 6 - Mature
Classifier: Environment :: Console
Classifier: Intended Audience :: Developers
Classifier: Operating System :: Unix
Classifier: Topic :: Software Development :: Quality Assurance
Classifier: Programming Language :: Python :: 2.6
Classifier: Programming Language :: Python :: 2.7
Classifier: Programming Language :: Python :: 3.3
Classifier: Programming Language :: Python :: 3.4
Classifier: Programming Language :: Python :: 3.5
Classifier: Programming Language :: Python :: 3.6
